freshspark/__init__.py
freshspark/__main__.py
freshspark/core.py
freshspark-0.1.0.dist-info/METADATA
freshspark-0.1.0.dist-info/WHEEL
freshspark-0.1.0.dist-info/entry_points.txt
freshspark-0.1.0.dist-info/top_level.txt
freshspark-0.1.0.dist-info/RECORD
