Metadata-Version: 2.4
Name: freshspark
Version: 0.1.0
Summary: Create truly fresh local Spark sessions with isolated temp dirs and reliable teardown.
Author: Odos Matthews
Project-URL: Homepage, https://github.com/eddiethedean/freshspark
Project-URL: Issues, https://github.com/eddiethedean/freshspark/issues
Keywords: pyspark,spark,spark-session,spark local,spark cleanup
Classifier: Programming Language :: Python :: 3
Classifier: Programming Language :: Python :: 3 :: Only
Classifier: License :: OSI Approved :: Apache Software License
Classifier: Development Status :: 3 - Alpha
Classifier: Intended Audience :: Developers
Classifier: Topic :: Software Development :: Libraries
Requires-Python: >=3.8
Requires-Dist: pyspark>=3.3
